{
    "id":"0xFBac31F68390fD62d6ff7dC9778688C21d672B54",
    "name":"GIGACHAD SD",
    "symbol":"GIGACHAD",
    "type":"BEP20",
    "decimals":9,
    "description":"The market cap dictates if the Max Sell limit per transaction is lowered or raised. The max sell is raised (or lowered) by 1 trillion, every day, until it matches that multiple. Exemple: 45 000$ market cap = 45 trillions max sell per transaction.",
    "explorer":"https://bscscan.com/address/0xFBac31F68390fD62d6ff7dC9778688C21d672B54",
    "reflections":true
}